llama_index/core/__init__.py
llama_index/core/py.typed
llama_index/core/schema.py
llama_index/core/bridge/BUILD
llama_index/core/bridge/__init__.py
llama_index/core/bridge/pydantic.py
llama_index/core/bridge/pydantic_core.py
llama_index/core/instrumentation/__init__.py
llama_index/core/instrumentation/base_handler.py
llama_index/core/instrumentation/dispatcher.py
llama_index/core/instrumentation/event_handlers/__init__.py
llama_index/core/instrumentation/event_handlers/base.py
llama_index/core/instrumentation/event_handlers/null.py
llama_index/core/instrumentation/events/BUILD
llama_index/core/instrumentation/events/__init__.py
llama_index/core/instrumentation/events/base.py
llama_index/core/instrumentation/events/span.py
llama_index/core/instrumentation/span/BUILD
llama_index/core/instrumentation/span/__init__.py
llama_index/core/instrumentation/span/base.py
llama_index/core/instrumentation/span/simple.py
llama_index/core/instrumentation/span_handlers/BUILD
llama_index/core/instrumentation/span_handlers/__init__.py
llama_index/core/instrumentation/span_handlers/base.py
llama_index/core/instrumentation/span_handlers/null.py
llama_index/core/instrumentation/span_handlers/simple.py
llama_index/core/workflow/__init__.py
llama_index/core/workflow/checkpointer.py
llama_index/core/workflow/context.py
llama_index/core/workflow/context_serializers.py
llama_index/core/workflow/decorators.py
llama_index/core/workflow/errors.py
llama_index/core/workflow/events.py
llama_index/core/workflow/handler.py
llama_index/core/workflow/retry_policy.py
llama_index/core/workflow/service.py
llama_index/core/workflow/types.py
llama_index/core/workflow/utils.py
llama_index/core/workflow/workflow.py
llama_index_workflow-1.0.1.dist-info/METADATA
llama_index_workflow-1.0.1.dist-info/WHEEL
llama_index_workflow-1.0.1.dist-info/licenses/LICENSE
llama_index_workflow-1.0.1.dist-info/RECORD
