Metadata-Version: 2.4
Name: llama-index-workflow
Version: 1.0.1
Summary: Lightweight fork of LlamaIndex's workflow module, offering powerful event-driven orchestration without the full llama-index-core dependencies.
Project-URL: Repository, https://github.com/maltehedderich/llama-index-workflow
Project-URL: Issue Tracker, https://github.com/maltehedderich/llama-index-workflow/issues
Author-email: Malte Hedderich <malte@hedderich.pro>
License: MIT
License-File: LICENSE
Classifier: License :: OSI Approved :: MIT License
Classifier: Operating System :: OS Independent
Classifier: Programming Language :: Python :: 3
Requires-Python: >=3.9
Requires-Dist: deprecated>=1.2.18
Requires-Dist: pydantic>=2.10.6
Requires-Dist: wrapt>=1.17.2
